seq2onehot/__init__.py
seq2onehot/main.py
seq2onehot-0.0.1.dist-info/LICENSE
seq2onehot-0.0.1.dist-info/METADATA
seq2onehot-0.0.1.dist-info/WHEEL
seq2onehot-0.0.1.dist-info/entry_points.txt
seq2onehot-0.0.1.dist-info/top_level.txt
seq2onehot-0.0.1.dist-info/RECORD
