Metadata-Version: 2.1
Name: seq2onehot
Version: 0.0.1
Summary: encoding a biological sequence to a one-hot numpy array
Home-page: https://github.com/akikuno/seq2onehot
Author: Akihiro Kuno
Author-email: akuno@md.tsukuba.ac.jp
License: UNKNOWN
Platform: UNKNOWN
Classifier: Programming Language :: Python :: 3
Classifier: License :: OSI Approved :: MIT License
Classifier: Operating System :: OS Independent
Requires-Python: >=3.7
License-File: LICENSE
Requires-Dist: numpy
